setup.py
stl/__init__.py
stl/ascii.py
stl/binary.py
stl/types.py
stl.egg-info/PKG-INFO
stl.egg-info/SOURCES.txt
stl.egg-info/dependency_links.txt
stl.egg-info/top_level.txt