Metadata-Version: 1.1
Name: stl
Version: 0.0.2
Summary: Read and write STL 3D geometry files in both the ASCII and the binary flavor
Home-page: UNKNOWN
Author: Martin Atkins
Author-email: mart@degeneration.co.uk
License: UNKNOWN
Platform: UNKNOWN
Classifier: License :: OSI Approved :: MIT License
Classifier: Intended Audience :: Developers
